umap/__init__.py
umap/admin.py
umap/apps.py
umap/asgi.py
umap/autocomplete.py
umap/context_processors.py
umap/decorators.py
umap/fields.py
umap/forms.py
umap/managers.py
umap/middleware.py
umap/models.py
umap/urls.py
umap/utils.py
umap/views.py
umap/wsgi.py
umap/bin/__init__.py
umap/locale/am_ET/LC_MESSAGES/django.mo
umap/locale/am_ET/LC_MESSAGES/django.po
umap/locale/ar/LC_MESSAGES/django.mo
umap/locale/ar/LC_MESSAGES/django.po
umap/locale/ast/LC_MESSAGES/django.mo
umap/locale/ast/LC_MESSAGES/django.po
umap/locale/bg/LC_MESSAGES/django.mo
umap/locale/bg/LC_MESSAGES/django.po
umap/locale/br/LC_MESSAGES/django.mo
umap/locale/br/LC_MESSAGES/django.po
umap/locale/ca/LC_MESSAGES/django.mo
umap/locale/ca/LC_MESSAGES/django.po
umap/locale/cs_CZ/LC_MESSAGES/django.mo
umap/locale/cs_CZ/LC_MESSAGES/django.po
umap/locale/da/LC_MESSAGES/django.mo
umap/locale/da/LC_MESSAGES/django.po
umap/locale/de/LC_MESSAGES/django.mo
umap/locale/de/LC_MESSAGES/django.po
umap/locale/el/LC_MESSAGES/django.mo
umap/locale/el/LC_MESSAGES/django.po
umap/locale/en/LC_MESSAGES/django.mo
umap/locale/en/LC_MESSAGES/django.po
umap/locale/es/LC_MESSAGES/django.mo
umap/locale/es/LC_MESSAGES/django.po
umap/locale/et/LC_MESSAGES/django.mo
umap/locale/et/LC_MESSAGES/django.po
umap/locale/eu/LC_MESSAGES/django.mo
umap/locale/eu/LC_MESSAGES/django.po
umap/locale/fa_IR/LC_MESSAGES/django.mo
umap/locale/fa_IR/LC_MESSAGES/django.po
umap/locale/fi/LC_MESSAGES/django.mo
umap/locale/fi/LC_MESSAGES/django.po
umap/locale/fr/LC_MESSAGES/django.mo
umap/locale/fr/LC_MESSAGES/django.po
umap/locale/gl/LC_MESSAGES/django.mo
umap/locale/gl/LC_MESSAGES/django.po
umap/locale/he/LC_MESSAGES/django.mo
umap/locale/he/LC_MESSAGES/django.po
umap/locale/hr/LC_MESSAGES/django.mo
umap/locale/hr/LC_MESSAGES/django.po
umap/locale/hu/LC_MESSAGES/django.mo
umap/locale/hu/LC_MESSAGES/django.po
umap/locale/id/LC_MESSAGES/django.mo
umap/locale/id/LC_MESSAGES/django.po
umap/locale/is/LC_MESSAGES/django.mo
umap_project-3.5.0.dist-info/METADATA
umap_project-3.5.0.dist-info/WHEEL
umap_project-3.5.0.dist-info/entry_points.txt
umap_project-3.5.0.dist-info/licenses/LICENSE
umap_project-3.5.0.dist-info/RECORD
