Metadata-Version: 2.4
Name: umap-project
Version: 3.5.0
Summary: Create maps with OpenStreetMap layers in a minute and embed them in your site.
Author-email: Yohan Boniface <yb@enix.org>
Maintainer-email: David Larlet <david@larlet.fr>
License-File: LICENSE
Keywords: django,geodjango,leaflet,map,openstreetmap
Classifier: Development Status :: 4 - Beta
Classifier: Intended Audience :: Developers
Classifier: Operating System :: OS Independent
Classifier: Programming Language :: Python
Classifier: Programming Language :: Python :: 3 :: Only
Classifier: Programming Language :: Python :: 3.10
Classifier: Programming Language :: Python :: 3.11
Classifier: Programming Language :: Python :: 3.12
Classifier: Topic :: Software Development :: Libraries :: Python Modules
Requires-Python: >=3.10
Requires-Dist: django-agnocomplete==2.2.0
Requires-Dist: django-environ==0.12.0
Requires-Dist: django-probes==1.7.0
Requires-Dist: django<6.0,>=5.1
Requires-Dist: pillow==12.0.0
Requires-Dist: psycopg==3.2.13
Requires-Dist: rcssmin==1.2.2
Requires-Dist: requests==2.32.5
Requires-Dist: rjsmin==1.2.5
Requires-Dist: social-auth-app-django==5.6.0
Requires-Dist: social-auth-core==4.8.1
Provides-Extra: deploy
Requires-Dist: django==5.2.9; extra == 'deploy'
Provides-Extra: dev
Requires-Dist: django==5.2.9; extra == 'dev'
Requires-Dist: djlint==1.36.4; extra == 'dev'
Requires-Dist: hatch==1.15.1; extra == 'dev'
Requires-Dist: isort==7.0.0; extra == 'dev'
Requires-Dist: mkdocs-material==9.7.0; extra == 'dev'
Requires-Dist: mkdocs-static-i18n==1.3.0; extra == 'dev'
Requires-Dist: mkdocs==1.6.1; extra == 'dev'
Requires-Dist: pymdown-extensions==10.17.1; extra == 'dev'
Requires-Dist: ruff==0.14.6; extra == 'dev'
Requires-Dist: vermin==1.7.0; extra == 'dev'
Provides-Extra: s3
Requires-Dist: django-storages[s3]==1.14.6; extra == 's3'
Provides-Extra: sync
Requires-Dist: pydantic==2.12.3; extra == 'sync'
Requires-Dist: redis==7.1.0; extra == 'sync'
Requires-Dist: uvicorn==0.38.0; extra == 'sync'
Requires-Dist: websockets==15.0.1; extra == 'sync'
Provides-Extra: test
Requires-Dist: daphne==4.2.1; extra == 'test'
Requires-Dist: factory-boy==3.3.3; extra == 'test'
Requires-Dist: moto[s3]==5.1.14; extra == 'test'
Requires-Dist: playwright>=1.39; extra == 'test'
Requires-Dist: pytest-django==4.11.1; extra == 'test'
Requires-Dist: pytest-playwright==0.7.2; extra == 'test'
Requires-Dist: pytest-rerunfailures==16.1; extra == 'test'
Requires-Dist: pytest-xdist<4,>=3.5.0; extra == 'test'
Requires-Dist: pytest==8.4.2; extra == 'test'
Provides-Extra: yunohost
Requires-Dist: django-yunohost-integration==0.10.9; extra == 'yunohost'
Requires-Dist: django==5.1.15; extra == 'yunohost'
Requires-Dist: uvicorn==0.38.0; extra == 'yunohost'
